logger_alionic/__init__.py
logger_alionic/logger.py
logger_alionic-0.1.0.dist-info/METADATA
logger_alionic-0.1.0.dist-info/WHEEL
logger_alionic-0.1.0.dist-info/top_level.txt
logger_alionic-0.1.0.dist-info/RECORD
